{
  "offset":1.45,
  "bpm":0.33333333333,
  "notes":[{"time":0,"type":1,"position":5,"double":0,"holdtime":6.0},
{"time":1.0,"type":0,"position":3,"double":0},
{"time":2.0,"type":0,"position":8,"double":0},
{"time":3.0,"type":0,"position":8,"double":0},
{"time":4.0,"type":0,"position":3,"double":0},
{"time":5.0,"type":0,"position":8,"double":0},
{"time":6.0,"type":0,"position":8,"double":0},
{"time":8.0,"type":0,"position":6,"double":0},
{"time":9.0,"type":0,"position":6,"double":0},
{"time":10.0,"type":0,"position":1,"double":0},
{"time":11.0,"type":0,"position":1,"double":0},
{"time":12.0,"type":0,"position":6,"double":0},
{"time":13.0,"type":0,"position":1,"double":0},
{"time":14.0,"type":0,"position":1,"double":0},
{"time":16.0,"type":1,"position":5,"double":0,"holdtime":6.0},
{"time":17.0,"type":0,"position":4,"double":0},
{"time":18.0,"type":0,"position":7,"double":0},
{"time":19.0,"type":0,"position":7,"double":0},
{"time":20.0,"type":0,"position":4,"double":0},
{"time":21.0,"type":0,"position":7,"double":0},
{"time":22.0,"type":0,"position":7,"double":0},
{"time":24.0,"type":0,"position":5,"double":0},
{"time":25.0,"type":0,"position":5,"double":0},
{"time":26.0,"type":0,"position":2,"double":0},
{"time":27.0,"type":0,"position":2,"double":0},
{"time":28.0,"type":0,"position":5,"double":0},
{"time":31.0,"type":0,"position":1,"double":0},
{"time":32.0,"type":0,"position":2,"double":1},
{"time":32.0,"type":0,"position":6,"double":1},
{"time":32.75,"type":0,"position":3,"double":1},
{"time":32.75,"type":0,"position":5,"double":1},
{"time":33.5,"type":0,"position":4,"double":0},
{"time":34.0,"type":0,"position":3,"double":1},
{"time":34.0,"type":0,"position":7,"double":1},
{"time":34.75,"type":0,"position":4,"double":1},
{"time":34.75,"type":0,"position":6,"double":1},
{"time":35.5,"type":0,"position":5,"double":0},
{"time":36.0,"type":0,"position":2,"double":1},
{"time":36.0,"type":0,"position":6,"double":1},
{"time":36.75,"type":0,"position":3,"double":1},
{"time":36.75,"type":0,"position":5,"double":1},
{"time":37.5,"type":0,"position":4,"double":0},
{"time":38.0,"type":0,"position":3,"double":1},
{"time":38.0,"type":0,"position":7,"double":1},
{"time":38.75,"type":0,"position":4,"double":1},
{"time":38.75,"type":0,"position":6,"double":1},
{"time":39.5,"type":0,"position":5,"double":0},
{"time":40.0,"type":0,"position":1,"double":1},
{"time":40.0,"type":0,"position":7,"double":1},
{"time":40.75,"type":0,"position":3,"double":1},
{"time":40.75,"type":0,"position":5,"double":1},
{"time":41.5,"type":0,"position":4,"double":0},
{"time":42.0,"type":0,"position":2,"double":1},
{"time":42.0,"type":0,"position":8,"double":1},
{"time":42.75,"type":0,"position":4,"double":1},
{"time":42.75,"type":0,"position":6,"double":1},
{"time":43.5,"type":0,"position":5,"double":0},
{"time":44.0,"type":0,"position":1,"double":1},
{"time":44.0,"type":0,"position":7,"double":1},
{"time":44.75,"type":0,"position":2,"double":0},
{"time":45.5,"type":0,"position":7,"double":0},
{"time":48.0,"type":0,"position":2,"double":1},
{"time":48.0,"type":0,"position":6,"double":1},
{"time":48.75,"type":0,"position":3,"double":1},
{"time":48.75,"type":0,"position":5,"double":1},
{"time":49.5,"type":0,"position":4,"double":0},
{"time":50.0,"type":0,"position":3,"double":1},
{"time":50.0,"type":0,"position":7,"double":1},
{"time":50.75,"type":0,"position":4,"double":1},
{"time":50.75,"type":0,"position":6,"double":1},
{"time":51.5,"type":0,"position":5,"double":0},
{"time":52.0,"type":0,"position":2,"double":1},
{"time":52.0,"type":0,"position":6,"double":1},
{"time":52.75,"type":0,"position":3,"double":1},
{"time":52.75,"type":0,"position":5,"double":1},
{"time":53.5,"type":0,"position":4,"double":0},
{"time":54.0,"type":0,"position":3,"double":1},
{"time":54.0,"type":0,"position":7,"double":1},
{"time":54.75,"type":0,"position":4,"double":1},
{"time":54.75,"type":0,"position":6,"double":1},
{"time":55.5,"type":0,"position":5,"double":0},
{"time":56.0,"type":0,"position":1,"double":1},
{"time":56.0,"type":0,"position":7,"double":1},
{"time":56.75,"type":0,"position":2,"double":1},
{"time":56.75,"type":0,"position":6,"double":1},
{"time":57.5,"type":0,"position":4,"double":0},
{"time":58.0,"type":0,"position":2,"double":1},
{"time":58.0,"type":0,"position":8,"double":1},
{"time":58.75,"type":0,"position":3,"double":1},
{"time":58.75,"type":0,"position":7,"double":1},
{"time":59.5,"type":0,"position":5,"double":0},
{"time":60.0,"type":0,"position":3,"double":1},
{"time":60.0,"type":0,"position":4,"double":1},
{"time":60.75,"type":0,"position":2,"double":1},
{"time":60.75,"type":0,"position":5,"double":1},
{"time":61.5,"type":0,"position":7,"double":1},
{"time":61.5,"type":0,"position":8,"double":1},
{"time":62.0,"type":0,"position":5,"double":1},
{"time":62.0,"type":0,"position":6,"double":1},
{"time":62.75,"type":0,"position":4,"double":1},
{"time":62.75,"type":0,"position":7,"double":1},
{"time":63.5,"type":0,"position":1,"double":1},
{"time":63.5,"type":0,"position":2,"double":1},
{"time":95.0,"type":0,"position":8,"double":0},
{"time":96.0,"type":0,"position":7,"double":0},
{"time":96.5,"type":0,"position":7,"double":0},
{"time":97.0,"type":0,"position":6,"double":0},
{"time":97.5,"type":0,"position":6,"double":0},
{"time":98.0,"type":0,"position":5,"double":0},
{"time":98.5,"type":0,"position":5,"double":0},
{"time":99.0,"type":0,"position":4,"double":0},
{"time":99.5,"type":0,"position":4,"double":0},
{"time":100.0,"type":0,"position":3,"double":0},
{"time":100.5,"type":0,"position":2,"double":0},
{"time":101.5,"type":0,"position":8,"double":0},
{"time":104.0,"type":0,"position":2,"double":0},
{"time":104.5,"type":0,"position":2,"double":0},
{"time":105.0,"type":0,"position":3,"double":0},
{"time":105.5,"type":0,"position":3,"double":0},
{"time":106.0,"type":0,"position":4,"double":0},
{"time":106.5,"type":0,"position":4,"double":0},
{"time":107.0,"type":0,"position":5,"double":0},
{"time":107.5,"type":0,"position":5,"double":0},
{"time":108.0,"type":0,"position":6,"double":0},
{"time":108.5,"type":0,"position":7,"double":0},
{"time":109.5,"type":0,"position":1,"double":0},
{"time":112.0,"type":0,"position":5,"double":0},
{"time":112.5,"type":0,"position":5,"double":0},
{"time":113.0,"type":0,"position":4,"double":0},
{"time":113.5,"type":0,"position":4,"double":0},
{"time":114.0,"type":0,"position":6,"double":0},
{"time":114.5,"type":0,"position":6,"double":0},
{"time":115.0,"type":0,"position":3,"double":0},
{"time":115.5,"type":0,"position":3,"double":0},
{"time":116.0,"type":0,"position":7,"double":0},
{"time":116.5,"type":0,"position":2,"double":0},
{"time":119.0,"type":0,"position":4,"double":1},
{"time":119.0,"type":0,"position":5,"double":1},
{"time":120.0,"type":0,"position":7,"double":0},
{"time":120.5,"type":0,"position":6,"double":0},
{"time":121.0,"type":0,"position":5,"double":0},
{"time":121.5,"type":0,"position":4,"double":0},
{"time":122.0,"type":0,"position":2,"double":0},
{"time":122.5,"type":0,"position":3,"double":0},
{"time":123.0,"type":0,"position":4,"double":0},
{"time":123.5,"type":0,"position":5,"double":0},
{"time":124.0,"type":0,"position":6,"double":0},
{"time":125.0,"type":0,"position":4,"double":1},
{"time":125.0,"type":0,"position":7,"double":1},
{"time":125.5,"type":0,"position":4,"double":1},
{"time":125.5,"type":0,"position":7,"double":1},
{"time":126.0,"type":0,"position":2,"double":1},
{"time":126.0,"type":0,"position":5,"double":1},
{"time":126.5,"type":0,"position":2,"double":1},
{"time":126.5,"type":0,"position":5,"double":1},
{"time":127.0,"type":0,"position":1,"double":1},
{"time":127.0,"type":0,"position":8,"double":1},
{"time":127.5,"type":0,"position":1,"double":1},
{"time":127.5,"type":0,"position":8,"double":1},
{"time":128.0,"type":0,"position":2,"double":0},
{"time":128.5,"type":0,"position":4,"double":0},
{"time":129.0,"type":0,"position":2,"double":0},
{"time":129.5,"type":0,"position":4,"double":0},
{"time":130.0,"type":0,"position":1,"double":0},
{"time":130.5,"type":0,"position":4,"double":0},
{"time":131.0,"type":0,"position":1,"double":0},
{"time":131.5,"type":0,"position":4,"double":0},
{"time":132.0,"type":0,"position":8,"double":0},
{"time":132.5,"type":0,"position":4,"double":0},
{"time":133.0,"type":0,"position":8,"double":0},
{"time":133.5,"type":0,"position":4,"double":0},
{"time":136.0,"type":0,"position":7,"double":0},
{"time":136.5,"type":0,"position":5,"double":0},
{"time":137.0,"type":0,"position":7,"double":0},
{"time":137.5,"type":0,"position":5,"double":0},
{"time":138.0,"type":0,"position":8,"double":0},
{"time":138.5,"type":0,"position":5,"double":0},
{"time":139.0,"type":0,"position":8,"double":0},
{"time":139.5,"type":0,"position":5,"double":0},
{"time":140.0,"type":0,"position":1,"double":0},
{"time":140.5,"type":0,"position":5,"double":0},
{"time":141.0,"type":0,"position":1,"double":0},
{"time":141.5,"type":0,"position":5,"double":0},
{"time":144.0,"type":1,"position":6,"double":0,"holdtime":1.5},
{"time":144.75,"type":0,"position":5,"double":0},
{"time":145.5,"type":0,"position":7,"double":0},
{"time":147.0,"type":0,"position":1,"double":0},
{"time":148.0,"type":1,"position":3,"double":0,"holdtime":1.5},
{"time":148.75,"type":0,"position":4,"double":0},
{"time":149.5,"type":0,"position":2,"double":0},
{"time":151.0,"type":0,"position":8,"double":0},
{"time":152.0,"type":0,"position":4,"double":1},
{"time":152.0,"type":0,"position":6,"double":1},
{"time":152.5,"type":0,"position":4,"double":1},
{"time":152.5,"type":0,"position":6,"double":1},
{"time":153.0,"type":0,"position":2,"double":1},
{"time":153.0,"type":0,"position":5,"double":1},
{"time":153.5,"type":0,"position":2,"double":1},
{"time":153.5,"type":0,"position":5,"double":1},
{"time":154.0,"type":0,"position":3,"double":1},
{"time":154.0,"type":0,"position":7,"double":1},
{"time":154.5,"type":0,"position":3,"double":1},
{"time":154.5,"type":0,"position":7,"double":1},
{"time":155.0,"type":0,"position":1,"double":1},
{"time":155.0,"type":0,"position":8,"double":1},
{"time":155.5,"type":0,"position":1,"double":1},
{"time":155.5,"type":0,"position":8,"double":1},
{"time":159.0,"type":0,"position":8,"double":0},
{"time":160.0,"type":1,"position":4,"double":0,"holdtime":4.0},
{"time":162.0,"type":0,"position":3,"double":0},
{"time":162.5,"type":0,"position":2,"double":0},
{"time":163.0,"type":0,"position":1,"double":0},
{"time":163.5,"type":0,"position":8,"double":0},
{"time":164.0,"type":1,"position":7,"double":0,"holdtime":4.0},
{"time":166.0,"type":0,"position":6,"double":0},
{"time":166.5,"type":0,"position":5,"double":0},
{"time":167.0,"type":0,"position":4,"double":0},
{"time":167.5,"type":0,"position":3,"double":0},
{"time":168.0,"type":1,"position":2,"double":0,"holdtime":4.0},
{"time":170.0,"type":0,"position":3,"double":0},
{"time":170.5,"type":0,"position":4,"double":0},
{"time":171.0,"type":0,"position":5,"double":0},
{"time":171.5,"type":0,"position":6,"double":0},
{"time":172.0,"type":1,"position":7,"double":0,"holdtime":4.0},
{"time":173.5,"type":0,"position":8,"double":0},
{"time":174.0,"type":0,"position":1,"double":0},
{"time":174.5,"type":0,"position":2,"double":0},
{"time":175.0,"type":0,"position":3,"double":0},
{"time":175.5,"type":0,"position":4,"double":0},
{"time":176.0,"type":1,"position":5,"double":0,"holdtime":4.0},
{"time":178.0,"type":0,"position":4,"double":0},
{"time":178.5,"type":0,"position":3,"double":0},
{"time":179.0,"type":0,"position":2,"double":0},
{"time":179.5,"type":0,"position":1,"double":0},
{"time":180.0,"type":1,"position":8,"double":0,"holdtime":4.0},
{"time":182.0,"type":0,"position":7,"double":0},
{"time":182.5,"type":0,"position":6,"double":0},
{"time":183.0,"type":0,"position":5,"double":0},
{"time":183.5,"type":0,"position":4,"double":0},
{"time":184.0,"type":1,"position":3,"double":0,"holdtime":4.0},
{"time":186.0,"type":0,"position":2,"double":0},
{"time":186.5,"type":0,"position":1,"double":0},
{"time":187.0,"type":0,"position":8,"double":0},
{"time":187.5,"type":0,"position":7,"double":0},
{"time":188.0,"type":1,"position":6,"double":0,"holdtime":4.0},
{"time":189.5,"type":0,"position":7,"double":0},
{"time":190.0,"type":0,"position":8,"double":0},
{"time":190.5,"type":0,"position":1,"double":0},
{"time":191.0,"type":0,"position":2,"double":0},
{"time":191.5,"type":0,"position":3,"double":0},
{"time":192.0,"type":0,"position":4,"double":0},
{"time":193.0,"type":0,"position":4,"double":0},
{"time":194.0,"type":0,"position":4,"double":0},
{"time":194.5,"type":0,"position":6,"double":0},
{"time":195.0,"type":0,"position":4,"double":0},
{"time":195.5,"type":0,"position":7,"double":0},
{"time":196.0,"type":0,"position":5,"double":1},
{"time":196.0,"type":0,"position":8,"double":1},
{"time":197.0,"type":0,"position":5,"double":0},
{"time":198.0,"type":0,"position":5,"double":0},
{"time":198.5,"type":0,"position":3,"double":0},
{"time":199.0,"type":0,"position":5,"double":0},
{"time":199.5,"type":0,"position":2,"double":0},
{"time":200.0,"type":0,"position":1,"double":1},
{"time":200.0,"type":0,"position":4,"double":1},
{"time":201.0,"type":0,"position":4,"double":0},
{"time":202.0,"type":0,"position":4,"double":0},
{"time":202.5,"type":0,"position":6,"double":0},
{"time":203.0,"type":0,"position":4,"double":0},
{"time":203.5,"type":0,"position":7,"double":0},
{"time":204.0,"type":0,"position":1,"double":1},
{"time":204.0,"type":0,"position":8,"double":1},
{"time":205.0,"type":0,"position":5,"double":0},
{"time":205.5,"type":0,"position":4,"double":0},
{"time":206.0,"type":0,"position":5,"double":0},
{"time":206.5,"type":0,"position":3,"double":0},
{"time":207.0,"type":0,"position":5,"double":0},
{"time":207.5,"type":0,"position":2,"double":0},
{"time":208.0,"type":0,"position":1,"double":1},
{"time":208.0,"type":0,"position":8,"double":1},
{"time":208.5,"type":0,"position":2,"double":0},
{"time":209.0,"type":0,"position":1,"double":1},
{"time":209.0,"type":0,"position":8,"double":1},
{"time":209.5,"type":0,"position":7,"double":0},
{"time":210.0,"type":0,"position":1,"double":1},
{"time":210.0,"type":0,"position":8,"double":1},
{"time":210.5,"type":0,"position":2,"double":0},
{"time":211.0,"type":0,"position":1,"double":1},
{"time":211.0,"type":0,"position":8,"double":1},
{"time":211.5,"type":0,"position":7,"double":0},
{"time":212.0,"type":0,"position":4,"double":1},
{"time":212.0,"type":0,"position":5,"double":1},
{"time":212.5,"type":0,"position":3,"double":0},
{"time":213.0,"type":0,"position":4,"double":1},
{"time":213.0,"type":0,"position":5,"double":1},
{"time":213.5,"type":0,"position":6,"double":0},
{"time":214.0,"type":0,"position":4,"double":1},
{"time":214.0,"type":0,"position":5,"double":1},
{"time":214.5,"type":0,"position":3,"double":0},
{"time":215.0,"type":0,"position":4,"double":1},
{"time":215.0,"type":0,"position":5,"double":1},
{"time":215.5,"type":0,"position":6,"double":0},
{"time":216.0,"type":0,"position":5,"double":1},
{"time":216.0,"type":0,"position":7,"double":1},
{"time":216.5,"type":0,"position":5,"double":1},
{"time":216.5,"type":0,"position":7,"double":1},
{"time":217.0,"type":0,"position":4,"double":1},
{"time":217.0,"type":0,"position":6,"double":1},
{"time":217.5,"type":0,"position":4,"double":1},
{"time":217.5,"type":0,"position":6,"double":1},
{"time":218.0,"type":0,"position":3,"double":1},
{"time":218.0,"type":0,"position":5,"double":1},
{"time":218.5,"type":0,"position":3,"double":1},
{"time":218.5,"type":0,"position":5,"double":1},
{"time":219.0,"type":0,"position":2,"double":1},
{"time":219.0,"type":0,"position":4,"double":1},
{"time":219.5,"type":0,"position":2,"double":1},
{"time":219.5,"type":0,"position":4,"double":1},
{"time":220.0,"type":0,"position":8,"double":0},
{"time":225.0,"type":0,"position":1,"double":0},
{"time":227.0,"type":0,"position":8,"double":0},
{"time":230.0,"type":0,"position":1,"double":0},
{"time":233.0,"type":0,"position":8,"double":0},
{"time":235.0,"type":0,"position":1,"double":0},
{"time":241.0,"type":0,"position":2,"double":0},
{"time":243.0,"type":0,"position":7,"double":0},
{"time":246.0,"type":0,"position":1,"double":0},
{"time":249.0,"type":0,"position":7,"double":0},
{"time":251.0,"type":0,"position":2,"double":0},
{"time":252.0,"type":0,"position":3,"double":1},
{"time":252.0,"type":0,"position":6,"double":1},
{"time":253.0,"type":0,"position":2,"double":1},
{"time":253.0,"type":0,"position":5,"double":1},
{"time":253.5,"type":0,"position":2,"double":1},
{"time":253.5,"type":0,"position":5,"double":1},
{"time":254.0,"type":0,"position":4,"double":1},
{"time":254.0,"type":0,"position":7,"double":1},
{"time":254.5,"type":0,"position":4,"double":1},
{"time":254.5,"type":0,"position":7,"double":1},
{"time":255.0,"type":0,"position":1,"double":1},
{"time":255.0,"type":0,"position":8,"double":1},
{"time":255.5,"type":0,"position":1,"double":1},
{"time":255.5,"type":0,"position":8,"double":1} ]
}
